odsbox/__init__.py
odsbox/asam_time.py
odsbox/bulk_reader.py
odsbox/con_i.py
odsbox/datamatrices_to_pandas.py
odsbox/jaquel.py
odsbox/jaquel_conversion_result.py
odsbox/model_cache.py
odsbox/model_suggestions.py
odsbox/py.typed
odsbox/security.py
odsbox/submatrix_to_pandas.py
odsbox/transaction.py
odsbox/unit_catalog.py
odsbox/unit_utils.py
odsbox/proto/README.md
odsbox/proto/__init__.py
odsbox/proto/ods_external_data_pb2.py
odsbox/proto/ods_external_data_pb2.pyi
odsbox/proto/ods_external_data_pb2_grpc.py
odsbox/proto/ods_notification_pb2.py
odsbox/proto/ods_notification_pb2.pyi
odsbox/proto/ods_pb2.py
odsbox/proto/ods_pb2.pyi
odsbox/proto/ods_security_pb2.py
odsbox/proto/ods_security_pb2.pyi
odsbox-1.0.16.dist-info/licenses/LICENSE
odsbox-1.0.16.dist-info/WHEEL
odsbox-1.0.16.dist-info/METADATA
odsbox-1.0.16.dist-info/RECORD
