Metadata-Version: 2.4
Name: odsbox
Version: 1.0.16
Summary: Toolbox for accessing ASAM ODS servers using the HTTP API
Keywords: asam,ods,measurement,data access,data science,data analysis
Author-email: Andreas Krantz <a.krantz@peak-solution.de>
Requires-Python: >=3.10.12
Classifier: Development Status :: 5 - Production/Stable
Classifier: Intended Audience :: Developers
Classifier: License :: OSI Approved :: MIT License
Classifier: Operating System :: OS Independent
Classifier: Programming Language :: Python :: 3 :: Only
Classifier: Programming Language :: Python :: 3.10
Classifier: Programming Language :: Python :: 3.11
Classifier: Programming Language :: Python :: 3.12
Classifier: Programming Language :: Python :: 3.13
Classifier: Topic :: Software Development :: Libraries :: Python Modules
Classifier: Topic :: Scientific/Engineering :: Information Analysis
Classifier: Typing :: Typed
License-File: LICENSE
Requires-Dist: protobuf>=5.27.0,<7.0.0
Requires-Dist: requests>=2.30.0,<3.0.0
Requires-Dist: pandas>=2.2.0,<3.0.0
Requires-Dist: grpcio>=1.59.3,<2.0.0 ; extra == "exd-data"
Requires-Dist: bandit[toml]==1.9.2 ; extra == "test"
Requires-Dist: black==25.12.0 ; extra == "test"
Requires-Dist: check-manifest==0.51 ; extra == "test"
Requires-Dist: flake8-bugbear==25.11.29 ; extra == "test"
Requires-Dist: flake8-docstrings ; extra == "test"
Requires-Dist: flake8-formatter_junit_xml ; extra == "test"
Requires-Dist: flake8 ; extra == "test"
Requires-Dist: flake8-pyproject ; extra == "test"
Requires-Dist: mypy==1.19.1 ; extra == "test"
Requires-Dist: pre-commit==4.5.1 ; extra == "test"
Requires-Dist: pylint==4.0.4 ; extra == "test"
Requires-Dist: pylint_junit ; extra == "test"
Requires-Dist: pytest-cov==7.0.0 ; extra == "test"
Requires-Dist: pytest-mock<3.15.2 ; extra == "test"
Requires-Dist: pytest-runner ; extra == "test"
Requires-Dist: pytest==9.0.2 ; extra == "test"
Requires-Dist: pytest-github-actions-annotate-failures ; extra == "test"
Requires-Dist: pytest-xdist ; extra == "test"
Requires-Dist: shellcheck-py==0.11.0.1 ; extra == "test"
Requires-Dist: types-requests>=2.30.0,<3.0.0 ; extra == "test"
Project-URL: Changelog, https://github.com/peak-solution/odsbox/releases
Project-URL: Documentation, https://peak-solution.github.io/odsbox
Project-URL: Homepage, https://github.com/peak-solution/odsbox/tree/main#readme
Project-URL: Repository, https://github.com/peak-solution/odsbox
Project-URL: Tracker, https://github.com/peak-solution/odsbox/issues
Provides-Extra: exd-data
Provides-Extra: test
